[{"place_id": 127888260, "licence": "Data \u00a9 OpenStreetMap contributors, ODbL 1.0. https://osm.org/copyright", "osm_type": "way", "osm_id": 110109636, "boundingbox": ["32.0222011", "32.0222453", "34.7726755", "34.7730661"], "lat": "32.0222011", "lon": "34.7730661", "display_name": "Gush Halav, Holon, Kiryat Avoda, Holon, Tel Aviv Subdistrict, Tel Aviv District, 5832337, Israel", "class": "highway", "type": "residential", "importance": 0.09999999999999998, "geojson": {"type": "LineString", "coordinates": [[34.7730661, 32.0222011], [34.7726755, 32.0222453]]}}, {"place_id": 116037825, "licence": "Data \u00a9 OpenStreetMap contributors, ODbL 1.0. https://osm.org/copyright", "osm_type": "way", "osm_id": 51546353, "boundingbox": ["32.0222453", "32.0224391", "34.7714532", "34.7726755"], "lat": "32.0222731", "lon": "34.7724999", "display_name": "Gush Halav, Holon, Kiryat Avoda, Holon, Tel Aviv Subdistrict, Tel Aviv District, 5832337, Israel", "class": "highway", "type": "residential", "importance": 0.09999999999999998, "geojson": {"type": "LineString", "coordinates": [[34.7714532, 32.0224391], [34.7724999, 32.0222731], [34.7726755, 32.0222453]]}}]